MANIFEST.in
README.rst
REQUIREMENTS.txt
setup.py
FliKISS.egg-info/PKG-INFO
FliKISS.egg-info/SOURCES.txt
FliKISS.egg-info/dependency_links.txt
FliKISS.egg-info/entry_points.txt
FliKISS.egg-info/requires.txt
FliKISS.egg-info/top_level.txt
flikiss/__init__.py
flikiss/config.py
flikiss/forms.py
flikiss/launcher.py
flikiss/login.py
flikiss/models.py
flikiss/utils.py
flikiss/views.py
flikiss/static/css/base.css
flikiss/static/css/flikiss.css
flikiss/static/css/font-awesome.min.css
flikiss/static/css/layout.css
flikiss/static/css/pygments.css
flikiss/static/css/skeleton.css
flikiss/static/fonts/FontAwesome.otf
flikiss/static/fonts/fontawesome-webfont.eot
flikiss/static/fonts/fontawesome-webfont.svg
flikiss/static/fonts/fontawesome-webfont.ttf
flikiss/static/fonts/fontawesome-webfont.woff
flikiss/static/img/favicon.png
flikiss/static/img/logo.png
flikiss/static/js/editor.js
flikiss/templates/base.html
flikiss/templates/edit.html
flikiss/templates/login.html
flikiss/templates/page.html