Metadata-Version: 1.1
Name: FliKISS
Version: 0.1
Summary: Wiki engine based on Markdown flat files powered by Flask
Home-page: http://projects.joacodepel.tk/flikiss/
Author: TROUVERIE Joachim
Author-email: joachim.trouverie@joacodepel.tk
License: UNKNOWN
Platform: UNKNOWN
Classifier: Programming Language :: Python
Classifier: Development Status :: 4 - Beta
Classifier: Environment :: Web Environment
Classifier: Framework :: Flask
Classifier: Topic :: Internet :: WWW/HTTP :: WSGI :: Application
Classifier: License :: OSI Approved :: GNU General Public License v3 or later (GPLv3+)
Classifier: Natural Language :: English
Classifier: Programming Language :: Python :: 2.7
